{"log_id": 3952769909056311439, "words_result_num": 13, "direction": 0, "words_result": [{"words": "10228\u3123", "location": {"width": 373, "left": 681, "height": 48, "top": 0}, "probability": {"average": 0.745721, "variance": 0.054154, "min": 0.369002}}, {"words": "176843\u4e0a2", "location": {"width": 390, "left": 686, "height": 61, "top": 50}, "probability": {"average": 0.783438, "variance": 0.034699, "min": 0.360895}}, {"words": "1030073", "location": {"width": 369, "left": 710, "height": 64, "top": 106}, "probability": {"average": 0.76964, "variance": 0.053981, "min": 0.35278}}, {"words": "13f91676", "location": {"width": 369, "left": 710, "height": 81, "top": 169}, "probability": {"average": 0.724739, "variance": 0.066502, "min": 0.369019}}, {"words": "K1444", "location": {"width": 351, "left": 728, "height": 75, "top": 260}, "probability": {"average": 0.758802, "variance": 0.032935, "min": 0.477466}}, {"words": "13356019", "location": {"width": 337, "left": 729, "height": 87, "top": 328}, "probability": {"average": 0.851767, "variance": 0.043211, "min": 0.384318}}, {"words": "136385642", "location": {"width": 329, "left": 738, "height": 78, "top": 434}, "probability": {"average": 0.960209, "variance": 0.008592, "min": 0.69857}}, {"words": "\u59d3\u540d\u7f57\u76fc\u59b9", "location": {"width": 223, "left": 200, "height": 46, "top": 602}, "probability": {"average": 0.999613, "variance": 0.0, "min": 0.998731}}, {"words": "\u6027\u522b\u5973\u6c11\u65cf\u5e03\u4f9d", "location": {"width": 349, "left": 195, "height": 46, "top": 670}, "probability": {"average": 0.989976, "variance": 0.000507, "min": 0.934859}}, {"words": "\u51fa\u751f1980\u5e74\u670819", "location": {"width": 400, "left": 190, "height": 48, "top": 734}, "probability": {"average": 0.976217, "variance": 0.002532, "min": 0.836329}}, {"words": "\u4f4f\u5740\u8d35\u5dde\u7701\u6674\u9686\u9e21\u6728\u89d2", "location": {"width": 489, "left": 185, "height": 51, "top": 805}, "probability": {"average": 0.850275, "variance": 0.031869, "min": 0.574556}}, {"words": "\u6751\u4e00\u7ec4", "location": {"width": 105, "left": 292, "height": 41, "top": 860}, "probability": {"average": 0.998813, "variance": 0.0, "min": 0.998158}}, {"words": "\u516c\u6c11\u8eab\u4efd\u53f7\u7801522324198001191302", "location": {"width": 783, "left": 175, "height": 58, "top": 988}, "probability": {"average": 0.999559, "variance": 2e-06, "min": 0.993367}}]}