{"words_result_num": 6, "direction": 1, "log_id": 5939182091718118414, "words_result": [{"location": {"left": 264, "top": 970, "width": 64, "height": 269}, "probability": {"min": 0.480227, "average": 0.890154, "variance": 0.042119}, "words": "n\u540d\u7530\u540e\u6c38"}, {"location": {"left": 355, "top": 867, "width": 55, "height": 370}, "probability": {"min": 0.378843, "average": 0.706597, "variance": 0.0847}, "words": "\u6027\u5219\u7537\u9662\u65d7\u58ee"}, {"location": {"left": 440, "top": 778, "width": 47, "height": 453}, "probability": {"min": 0.711303, "average": 0.971606, "variance": 0.006187}, "words": "\u51fa\u751f1981\u5e741\u670827\u65e5"}, {"location": {"left": 521, "top": 682, "width": 58, "height": 554}, "probability": {"min": 0.732957, "average": 0.963652, "variance": 0.006685}, "words": "\u4f4f\u5740\u4e91\u5357\u7701\u66f2\u9756\u5e02\u5e08\u5b97\u53bf\u9f99\u5e86"}, {"location": {"left": 567, "top": 677, "width": 66, "height": 434}, "probability": {"min": 0.480803, "average": 0.943461, "variance": 0.020209}, "words": "\u4e61\u9ed1\u5c14\u6751\u59d4\u4f1a\u4e2d\u5be8\u675110\u53f7"}, {"location": {"left": 736, "top": 375, "width": 69, "height": 858}, "probability": {"min": 0.986516, "average": 0.998556, "variance": 8e-06}, "words": "\u516c\u6c11\u8eab\u4efd\u53f7\u7801530323198101271311"}]}