{"log_id": 6782265552713245680, "direction": 3, "words_result": [{"probability": {"variance": 9e-06, "average": 0.995937, "min": 0.993136}, "words": "\u6bdb\u7231\u6c11", "location": {"width": 17, "height": 47, "top": 98, "left": 189}}, {"probability": {"variance": 0.000402, "average": 0.98755, "min": 0.95282}, "words": "\u7537\u6c11\u65cf\u6ee1", "location": {"width": 19, "height": 81, "top": 96, "left": 162}}, {"probability": {"variance": 0.001223, "average": 0.987336, "min": 0.876903}, "words": "\u751f1972\u5e742\u670828\u65e5", "location": {"width": 17, "height": 145, "top": 59, "left": 138}}, {"probability": {"variance": 0.002449, "average": 0.977061, "min": 0.820032}, "words": "\u4f73\u5740\u8fbd\u5b81\u7701\u51cc\u6d77\u5e02\u897f\u516b\u5343\u4e61\u559c", "location": {"width": 16, "height": 175, "top": 56, "left": 112}}, {"probability": {"variance": 0.028957, "average": 0.921448, "min": 0.540959}, "words": "\u9e4a\u6751101\u53f7", "location": {"width": 12, "height": 57, "top": 97, "left": 97}}, {"probability": {"variance": 6e-06, "average": 0.999109, "min": 0.987597}, "words": "\u516c\u6c11\u8eab\u4efd\u53f7\u780121072419720228361X", "location": {"width": 20, "height": 262, "top": 56, "left": 44}}], "words_result_num": 6}