{"log_id": 989412586758286640, "direction": 3, "words_result": [{"probability": {"variance": 5e-06, "average": 0.998588, "min": 0.99437}, "words": "\u59d3\u540d\u5b8b\u957f\u4e91", "location": {"width": 57, "height": 296, "top": 368, "left": 740}}, {"probability": {"variance": 0.001492, "average": 0.96921, "min": 0.896488}, "words": "\u6027\u522b\u7537\u6c11\u65cf\u6c49", "location": {"width": 53, "height": 403, "top": 367, "left": 652}}, {"probability": {"variance": 0.0, "average": 0.999263, "min": 0.99817}, "words": "\u51fa\u751f1956\u5e748\u670816\u65e5", "location": {"width": 57, "height": 494, "top": 373, "left": 566}}, {"probability": {"variance": 0.008813, "average": 0.971418, "min": 0.64625}, "words": "\u4f4f\u5740\u6c5f\u897f\u7701\u5409\u5b89\u5e02\u5409\u6c34\u53bf\u961c\u7530", "location": {"width": 51, "height": 582, "top": 373, "left": 480}}, {"probability": {"variance": 1e-06, "average": 0.999416, "min": 0.997947}, "words": "\u9547\u6751\u524d\u6751\u5357\u5df7\u81ea\u7136\u675173\u53f7", "location": {"width": 50, "height": 460, "top": 501, "left": 422}}, {"probability": {"variance": 8e-05, "average": 0.995049, "min": 0.961262}, "words": "\u516c\u6c11\u8eab\u4efd\u53f7\u7801362422195608162531", "location": {"width": 64, "height": 883, "top": 375, "left": 254}}], "words_result_num": 6}