{"log_id": 6741932780322700143, "words_result_num": 6, "direction": 3, "words_result": [{"words": "\u59d3\u540d\u5170\u4ef2\u5c71", "location": {"width": 66, "left": 756, "height": 332, "top": 266}, "probability": {"average": 0.995974, "variance": 2e-05, "min": 0.989172}}, {"words": "\u6027\u522b\u7537\u65cf\u6c49", "location": {"width": 53, "left": 664, "height": 452, "top": 273}, "probability": {"average": 0.993722, "variance": 0.000124, "min": 0.971498}}, {"words": "\u51fa\u751f1958\u5e745\u67084\u65e5", "location": {"width": 48, "left": 576, "height": 556, "top": 277}, "probability": {"average": 0.988027, "variance": 0.001225, "min": 0.877385}}, {"words": "\u4f4f\u5740\u6e56\u5317\u7701\u516c\u5b89\u53bf\u6768\u5bb6\u5382\u9547\u957f", "location": {"width": 56, "left": 472, "height": 674, "top": 272}, "probability": {"average": 0.99862, "variance": 7e-06, "min": 0.992593}}, {"words": "\u6c5f\u67511\u7ec4", "location": {"width": 54, "left": 404, "height": 180, "top": 419}, "probability": {"average": 0.998302, "variance": 1e-06, "min": 0.997135}}, {"words": "\u516c\u6c11\u8eab\u4efd\u53f7\u7801421022195805043033", "location": {"width": 67, "left": 217, "height": 1028, "top": 275}, "probability": {"average": 0.999598, "variance": 0.0, "min": 0.99775}}]}