{"log_id": 3799436649829424976, "direction": 0, "words_result": [{"probability": {"variance": 1e-06, "average": 0.999268, "min": 0.99785}, "words": "\u59d3\u540d\u5218\u7f8e\u660e", "location": {"width": 145, "height": 32, "top": 508, "left": 82}}, {"probability": {"variance": 0.033216, "average": 0.915633, "min": 0.508145}, "words": "\u6027\u522b\u7537\u6c11\u65cf\u7476", "location": {"width": 196, "height": 21, "top": 555, "left": 84}}, {"probability": {"variance": 3e-06, "average": 0.998584, "min": 0.994756}, "words": "\u51fa\u751f1969\u5e743\u670819\u65e5", "location": {"width": 240, "height": 28, "top": 590, "left": 86}}, {"probability": {"variance": 0.006027, "average": 0.974078, "min": 0.705706}, "words": "\u4f4f\u5740\u6e56\u5357\u7701\u84dd\u5c71\u53bf\u8346\u7af9\u4e61\u6c99\u843d", "location": {"width": 410, "height": 38, "top": 629, "left": 82}}, {"probability": {"variance": 0.000969, "average": 0.981854, "min": 0.927927}, "words": "\u6751\u827e\u516c\u7ec4", "location": {"width": 86, "height": 28, "top": 662, "left": 149}}, {"probability": {"variance": 2e-06, "average": 0.999472, "min": 0.99226}, "words": "\u516c\u6c11\u8eab\u4efd\u53f7\u7801431127196903194111", "location": {"width": 429, "height": 27, "top": 737, "left": 95}}], "words_result_num": 6}