{"words_result_num": 6, "direction": 0, "log_id": 3234227580089937134, "words_result": [{"location": {"left": 377, "top": 704, "width": 156, "height": 39}, "probability": {"min": 0.997921, "average": 0.999438, "variance": 1e-06}, "words": "\u59d3\u540d\u90d1\u534e\u7115"}, {"location": {"left": 382, "top": 760, "width": 205, "height": 23}, "probability": {"min": 0.968702, "average": 0.988148, "variance": 0.000153}, "words": "\u6027\u522b\u7537\u6c11\u65cf\u6c49"}, {"location": {"left": 378, "top": 802, "width": 263, "height": 26}, "probability": {"min": 0.994842, "average": 0.99925, "variance": 2e-06}, "words": "\u51fa\u751f1994\u5e743\u670822\u65e5"}, {"location": {"left": 379, "top": 847, "width": 312, "height": 31}, "probability": {"min": 0.971556, "average": 0.996749, "variance": 5.7e-05}, "words": "\u4f4f\u5740\u5e7f\u4e1c\u7701\u5434\u5ddd\u5e02\u9ec4\u5761\u9547\u6c11\u4e50"}, {"location": {"left": 448, "top": 880, "width": 132, "height": 30}, "probability": {"min": 0.993724, "average": 0.997817, "variance": 4e-06}, "words": "\u675171\u53f7102\u623f"}, {"location": {"left": 380, "top": 962, "width": 481, "height": 36}, "probability": {"min": 0.996993, "average": 0.999646, "variance": 0.0}, "words": "\u516c\u6c11\u8eab\u4efd\u53f7\u7801440883199403223514"}]}