{"log_id": 1109211210967609583, "words_result_num": 6, "direction": 0, "words_result": [{"words": "\u59d3\u540d\u53f6\u5fd7\u827a", "location": {"width": 64, "left": 32, "height": 14, "top": 177}, "probability": {"average": 0.967127, "variance": 0.004253, "min": 0.836692}}, {"words": "\u6027\u522b\u7537\u6c11\u6c49", "location": {"width": 86, "left": 32, "height": 11, "top": 197}, "probability": {"average": 0.956056, "variance": 0.006501, "min": 0.794952}}, {"words": "\u751f1980\u5e7411\u67084\u65e5", "location": {"width": 105, "left": 33, "height": 10, "top": 215}, "probability": {"average": 0.927731, "variance": 0.030933, "min": 0.375463}}, {"words": "\u589e\u5e7f\u4e1c\u7701\u6df1\u5e02\u9f99\u5c97\u533a\u7231\u9f99", "location": {"width": 126, "left": 32, "height": 10, "top": 235}, "probability": {"average": 0.944473, "variance": 0.025744, "min": 0.438061}}, {"words": "\u8def\u7199\u548c\u56ed2\u680b3\u5355\u51431202", "location": {"width": 94, "left": 59, "height": 10, "top": 247}, "probability": {"average": 0.935117, "variance": 0.023963, "min": 0.410576}}, {"words": "\u516c\u6c11\u8eab\u4efd\u53f7\u7801441624198011044459", "location": {"width": 196, "left": 30, "height": 11, "top": 282}, "probability": {"average": 0.996728, "variance": 8.2e-05, "min": 0.96306}}]}