{"log_id": 2478151344820020368, "direction": 0, "words_result": [{"probability": {"variance": 0.058049, "average": 0.732822, "min": 0.423831}, "words": "e\u8005\u5f20\u798f\u6837", "location": {"width": 282, "height": 68, "top": 780, "left": 126}}, {"probability": {"variance": 0.044895, "average": 0.666688, "min": 0.375113}, "words": "\u6027\u522b\u7537\u6c11\u65cf", "location": {"width": 338, "height": 45, "top": 877, "left": 122}}, {"probability": {"variance": 0.0, "average": 0.987092, "min": 0.987092}, "words": "N", "location": {"width": 38, "height": 23, "top": 925, "left": 345}}, {"probability": {"variance": 0.017167, "average": 0.899983, "min": 0.589321}, "words": "\u51fa\u751f1984\u5e7411\u67085\u65e5", "location": {"width": 486, "height": 59, "top": 948, "left": 114}}, {"probability": {"variance": 0.040047, "average": 0.840497, "min": 0.387242}, "words": "\u4f4f\u5740\u5e7f\u897f\u5317\u6f66\u5e02\u65b0\u5729\u9547\u4e0b\u5761\u6751", "location": {"width": 597, "height": 66, "top": 1032, "left": 104}}, {"probability": {"variance": 0.000334, "average": 0.975043, "min": 0.94405}, "words": "\u7ea2\u65d7\u7ec428\u53f7", "location": {"width": 220, "height": 53, "top": 1092, "left": 231}}, {"probability": {"variance": 0.000277, "average": 0.994988, "min": 0.915637}, "words": "\u516c\u6c11\u8eab\u4efd\u53f7\u7801450981198411051150", "location": {"width": 934, "height": 88, "top": 1242, "left": 87}}], "words_result_num": 7}