{"words_result_num": 13, "direction": 0, "log_id": 129561808222041454, "words_result": [{"location": {"left": 154, "top": 622, "width": 120, "height": 19}, "probability": {"min": 0.813858, "average": 0.84901, "variance": 0.004225}, "words": "S.GOMNGZ"}, {"location": {"left": 152, "top": 642, "width": 233, "height": 44}, "probability": {"min": 0.986864, "average": 0.996101, "variance": 2.4e-05}, "words": "\u59d3\u540d\u4f55\u6728\u751f"}, {"location": {"left": 357, "top": 689, "width": 79, "height": 19}, "probability": {"min": 0.466605, "average": 0.656618, "variance": 0.027969}, "words": "\u6cd5ZCU2"}, {"location": {"left": 153, "top": 719, "width": 318, "height": 35}, "probability": {"min": 0.98624, "average": 0.996863, "variance": 2.3e-05}, "words": "\u6027\u522b\u7537\u6c11\u65cf\u58ee"}, {"location": {"left": 153, "top": 754, "width": 56, "height": 19}, "probability": {"min": 0.924763, "average": 0.924763, "variance": 0.0}, "words": "SENG"}, {"location": {"left": 337, "top": 755, "width": 221, "height": 22}, "probability": {"min": 0.696227, "average": 0.852499, "variance": 0.013133}, "words": "NIENZ NYIED HAUH"}, {"location": {"left": 150, "top": 782, "width": 396, "height": 40}, "probability": {"min": 0.997563, "average": 0.99953, "variance": 0.0}, "words": "\u51fa\u751f1978\u5e7412\u67083\u65e5"}, {"location": {"left": 143, "top": 819, "width": 115, "height": 31}, "probability": {"min": 0.666636, "average": 0.666636, "variance": 0.0}, "words": "DEGYOUR"}, {"location": {"left": 151, "top": 852, "width": 473, "height": 42}, "probability": {"min": 0.988359, "average": 0.997921, "variance": 1.2e-05}, "words": "\u4f4f\u5740\u5e7f\u897f\u5b81\u660e\u53bf\u57ce\u4e2d\u9547\u9a6e\u9f99\u6751"}, {"location": {"left": 255, "top": 901, "width": 174, "height": 40}, "probability": {"min": 0.998773, "average": 0.999698, "variance": 0.0}, "words": "\u6d66\u679c\u5c6f34\u53f7"}, {"location": {"left": 183, "top": 990, "width": 85, "height": 17}, "probability": {"min": 0.799217, "average": 0.799217, "variance": 0.0}, "words": "NGHMINZ"}, {"location": {"left": 186, "top": 1010, "width": 135, "height": 18}, "probability": {"min": 0.500966, "average": 0.725861, "variance": 0.050578}, "words": "HPN HAUMAJ"}, {"location": {"left": 156, "top": 1029, "width": 713, "height": 41}, "probability": {"min": 0.998072, "average": 0.999735, "variance": 0.0}, "words": "\u516c\u6c11\u8eab\u4efd\u53f7\u7801452132197812030912"}]}