{"log_id": 1474365292389451439, "words_result_num": 5, "direction": 0, "words_result": [{"words": "\u4f55\u53d9\u8d24", "location": {"width": 29, "left": 86, "height": 12, "top": 154}, "probability": {"average": 0.996541, "variance": 5e-06, "min": 0.994464}}, {"words": "1961\u5e745\u67088\u65e5", "location": {"width": 64, "left": 87, "height": 10, "top": 186}, "probability": {"average": 0.925261, "variance": 0.003854, "min": 0.830722}}, {"words": "\u5065\u5e7f\u897f\u5c91\u5e02\u4e09\u5821\u9547\u6cb3\u8fb9\u6751", "location": {"width": 106, "left": 62, "height": 12, "top": 200}, "probability": {"average": 0.806946, "variance": 0.032101, "min": 0.506974}}, {"words": "\u4e00\u7ec461\u53f7", "location": {"width": 39, "left": 93, "height": 10, "top": 212}, "probability": {"average": 0.985297, "variance": 0.000267, "min": 0.954172}}, {"words": "\u516c\u6c11\u8eab\u4efd\u53f7\u7801452421196105082417", "location": {"width": 163, "left": 62, "height": 16, "top": 240}, "probability": {"average": 0.968513, "variance": 0.008683, "min": 0.545851}}]}