{"log_id": 8366471546432793967, "words_result_num": 7, "direction": 1, "words_result": [{"words": "SINGON", "location": {"width": 15, "left": 176, "height": 68, "top": 794}, "probability": {"average": 0.383526, "variance": 0.0, "min": 0.383526}}, {"words": "\u59d3\u540d\u83ab\u4f1f\u826f", "location": {"width": 35, "left": 188, "height": 178, "top": 684}, "probability": {"average": 0.999588, "variance": 0.0, "min": 0.998993}}, {"words": "\u6027\u522b\u7537\u6c11\u65cf\u58ee", "location": {"width": 31, "left": 243, "height": 242, "top": 619}, "probability": {"average": 0.982463, "variance": 0.001294, "min": 0.902064}}, {"words": "\u51fa\u751f1972\u5e743\u670829\u65e5", "location": {"width": 38, "left": 287, "height": 296, "top": 561}, "probability": {"average": 0.998209, "variance": 1e-05, "min": 0.989041}}, {"words": "\u4f4f\u5740\u5e7f\u897f\u90a3\u5761\u53bf\u767e\u5357\u4e61\u90a3\u5c9c\u6751", "location": {"width": 44, "left": 335, "height": 350, "top": 503}, "probability": {"average": 0.958116, "variance": 0.008212, "min": 0.697707}}, {"words": "\u90a3\u5c9c\u5c6f17\u53f7", "location": {"width": 30, "left": 376, "height": 130, "top": 641}, "probability": {"average": 0.993722, "variance": 7.1e-05, "min": 0.977986}}, {"words": "\u516c\u6c11\u8eab\u4efd\u53f7\u7801452627197203291670", "location": {"width": 62, "left": 445, "height": 514, "top": 328}, "probability": {"average": 0.999399, "variance": 1e-06, "min": 0.994726}}]}