{"log_id": 7032387218387661265, "words_result": [{"location": {"left": 518, "top": 210, "height": 194, "width": 37}, "words": "\u59d3\u540d\u7f57\u79c0\u82f1", "probability": {"variance": 2.2e-05, "average": 0.997345, "min": 0.988027}}, {"location": {"left": 502, "top": 371, "height": 70, "width": 16}, "words": "MINzZGUZ", "probability": {"variance": 0.0, "average": 0.738148, "min": 0.738148}}, {"location": {"left": 505, "top": 212, "height": 87, "width": 16}, "words": "SINGOBIEE", "probability": {"variance": 0.0, "average": 0.825397, "min": 0.825397}}, {"location": {"left": 464, "top": 211, "height": 258, "width": 33}, "words": "\u6027\u522b\u5973\u6c11\u65cf\u7476", "probability": {"variance": 7e-06, "average": 0.996787, "min": 0.993277}}, {"location": {"left": 447, "top": 494, "height": 46, "width": 15}, "words": "HAUH", "probability": {"variance": 0.0, "average": 0.980731, "min": 0.980731}}, {"location": {"left": 450, "top": 364, "height": 45, "width": 14}, "words": "NIENZ", "probability": {"variance": 0.0, "average": 0.878472, "min": 0.878472}}, {"location": {"left": 251, "top": 552, "height": 315, "width": 302}, "words": "Q", "probability": {"variance": 0.0, "average": 0.979439, "min": 0.979439}}, {"location": {"left": 411, "top": 211, "height": 319, "width": 32}, "words": "\u51fa\u751f1971\u5e741\u670813\u65e5", "probability": {"variance": 0.000126, "average": 0.994218, "min": 0.960246}}, {"location": {"left": 347, "top": 207, "height": 387, "width": 43}, "words": "\u4f4f\u5740\u5e7f\u897f\u4e1c\u5170\u53bf\u6b66\u7bc6\u9547\u7ea2\u91cc\u6751", "probability": {"variance": 2.5e-05, "average": 0.997738, "min": 0.981228}}, {"location": {"left": 317, "top": 291, "height": 145, "width": 30}, "words": "\u5f04\u4ecb\u5c6f20\u53f7", "probability": {"variance": 0.00082, "average": 0.985539, "min": 0.92166}}, {"location": {"left": 261, "top": 227, "height": 75, "width": 15}, "words": "NGHMIN\u2220", "probability": {"variance": 0.011525, "average": 0.859546, "min": 0.752192}}, {"location": {"left": 244, "top": 205, "height": 139, "width": 15}, "words": "SINHFWN HAUMAJ", "probability": {"variance": 0.002233, "average": 0.881331, "min": 0.834074}}, {"location": {"left": 202, "top": 201, "height": 592, "width": 45}, "words": "\u516c\u6c11\u8eab\u4efd\u53f7\u7801452728197101130325", "probability": {"variance": 0.0, "average": 0.999667, "min": 0.998347}}], "words_result_num": 13, "direction": 3}