{"direction": 3, "words_result_num": 6, "log_id": 2446374630752710705, "words_result": [{"words": "n\u540d\u6613\u5d07\u5e73", "probability": {"average": 0.927714, "variance": 0.010539, "min": 0.734374}, "location": {"left": 158, "width": 13, "height": 66, "top": 104}}, {"words": "\u6027\u522b\u7537\u6c11\u65d7\u6c49", "probability": {"average": 0.76688, "variance": 0.057483, "min": 0.436035}, "location": {"left": 138, "width": 13, "height": 88, "top": 105}}, {"words": "\u751f1966\u5e7410\u67086\u65e5", "probability": {"average": 0.916805, "variance": 0.016685, "min": 0.632981}, "location": {"left": 122, "width": 10, "height": 106, "top": 107}}, {"words": "\u4ef6\u5740\u5782\u5e86\u5e02\u57ab\u6c5f\u53bf\u592a\u5e73\u9547\u5929\u661f", "probability": {"average": 0.845232, "variance": 0.041202, "min": 0.44489}, "location": {"left": 103, "width": 11, "height": 127, "top": 106}}, {"words": "\u67513\u7ec44\u53f7", "probability": {"average": 0.904923, "variance": 0.019334, "min": 0.628333}, "location": {"left": 91, "width": 9, "height": 36, "top": 136}}, {"words": "\u516c\u6c11\u8eab\u4efd\u53f7\u7801512322196610066431", "probability": {"average": 0.987172, "variance": 0.000455, "min": 0.917584}, "location": {"left": 54, "width": 15, "height": 190, "top": 108}}]}