{"log_id": 2061820618594820976, "direction": 0, "words_result": [{"probability": {"variance": 0.0, "average": 0.977806, "min": 0.977806}, "words": "\u7c73", "location": {"width": 72, "height": 29, "top": 621, "left": 157}}, {"probability": {"variance": 0.0, "average": 0.999836, "min": 0.999465}, "words": "\u59d3\u540d\u7f57\u56fd\u53d1", "location": {"width": 224, "height": 42, "top": 641, "left": 158}}, {"probability": {"variance": 3e-06, "average": 0.998628, "min": 0.995598}, "words": "\u6027\u522b\u7537\u6c11\u65cf\u5f5d", "location": {"width": 310, "height": 36, "top": 718, "left": 159}}, {"probability": {"variance": 0.0, "average": 0.999811, "min": 0.999305}, "words": "\u51fa\u751f1979\u5e746\u670828\u65e5", "location": {"width": 385, "height": 33, "top": 786, "left": 161}}, {"probability": {"variance": 1.5e-05, "average": 0.997891, "min": 0.987513}, "words": "\u4f4f\u5740\u56db\u5ddd\u7701\u76d0\u6e90\u53bf\u6843\u5b50\u4e61\u73bb\u7483", "location": {"width": 462, "height": 37, "top": 857, "left": 160}}, {"probability": {"variance": 0.0, "average": 0.999659, "min": 0.999179}, "words": "\u67517\u7ec436\u53f7", "location": {"width": 179, "height": 35, "top": 903, "left": 265}}, {"probability": {"variance": 0.000993, "average": 0.938483, "min": 0.906966}, "words": "\u624b\u56fd", "location": {"width": 168, "height": 30, "top": 999, "left": 164}}, {"probability": {"variance": 0.0, "average": 0.999735, "min": 0.997589}, "words": "\u516c\u6c11\u8eab\u4efd\u53f7\u7801513423197906284179", "location": {"width": 703, "height": 38, "top": 1028, "left": 166}}], "words_result_num": 8}