{"log_id": 7735573057102484815, "words_result_num": 7, "direction": 3, "words_result": [{"words": "\u59d3\u540d\u6f58\u6c34\u59b9", "location": {"width": 45, "left": 717, "height": 234, "top": 456}, "probability": {"average": 0.999373, "variance": 0.0, "min": 0.998733}}, {"words": "\u4e00\u6027", "location": {"width": 64, "left": 636, "height": 74, "top": 442}, "probability": {"average": 0.708962, "variance": 0.080976, "min": 0.424399}}, {"words": "\u522b\u5973\u6c11\u65cf\u6c34", "location": {"width": 42, "left": 650, "height": 271, "top": 507}, "probability": {"average": 0.998441, "variance": 3e-06, "min": 0.995173}}, {"words": "\u51fa\u751f1983\u5e741\u67088\u65e5", "location": {"width": 44, "left": 588, "height": 392, "top": 464}, "probability": {"average": 0.991694, "variance": 0.000467, "min": 0.923894}}, {"words": "\u4f4f\u5740\u8d35\u5dde\u7701\u8354\u6ce2\u53bf\u4f73\u8363\u9547\u5c9c\u9c9c", "location": {"width": 57, "left": 511, "height": 472, "top": 464}, "probability": {"average": 0.994614, "variance": 8.6e-05, "min": 0.972987}}, {"words": "\u6751\u4e8c\u7ec435\u53f7", "location": {"width": 51, "left": 467, "height": 183, "top": 570}, "probability": {"average": 0.993943, "variance": 0.000106, "min": 0.971093}}, {"words": "\u516c\u6c11\u8eab\u4efd\u53f7\u7801522722198301081024", "location": {"width": 85, "left": 329, "height": 715, "top": 470}, "probability": {"average": 0.999484, "variance": 2e-06, "min": 0.992638}}]}