{"log_id": 2525922091466142320, "direction": 3, "words_result": [{"probability": {"variance": 0.0, "average": 0.99944, "min": 0.998703}, "words": "\u59d3\u540d\u9648\u5fd7\u6e05", "location": {"width": 55, "height": 283, "top": 402, "left": 723}}, {"probability": {"variance": 0.023166, "average": 0.922758, "min": 0.583217}, "words": "\u6027\u522b\u7537\u6c11\u65cf\u5f5d", "location": {"width": 52, "height": 384, "top": 404, "left": 639}}, {"probability": {"variance": 3e-06, "average": 0.99866, "min": 0.993961}, "words": "\u51fa\u751f1956\u5e7412\u67089\u65e5", "location": {"width": 45, "height": 472, "top": 406, "left": 564}}, {"probability": {"variance": 4e-06, "average": 0.998213, "min": 0.993327}, "words": "\u4f4f\u5740\u4e91\u5357\u7701\u6587\u5c71\u58ee\u65cf\u82d7\u65cf\u81ea\u6cbb", "location": {"width": 46, "height": 565, "top": 406, "left": 476}}, {"probability": {"variance": 0.011294, "average": 0.957178, "min": 0.630308}, "words": "\u5dde\u5e7f\u5357\u53bf\u6768\u67f3\u4e95\u4e61\u6768\u67f3\u4e95", "location": {"width": 45, "height": 440, "top": 530, "left": 421}}, {"probability": {"variance": 2e-06, "average": 0.998877, "min": 0.995675}, "words": "\u6751\u6c11\u59d4\u4e5d\u827e1\u5c0f\u7ec4", "location": {"width": 45, "height": 308, "top": 530, "left": 365}}, {"probability": {"variance": 2e-05, "average": 0.998055, "min": 0.979679}, "words": "\u516c\u6c11\u8eab\u4efd\u53f7\u780153262719561209111X", "location": {"width": 52, "height": 862, "top": 410, "left": 263}}], "words_result_num": 7}