{"direction": 3, "words_result_num": 7, "log_id": 6825373636944034289, "words_result": [{"words": "\u5979\u540d\u5218\u5fb7\u65ed", "probability": {"average": 0.908829, "variance": 0.032912, "min": 0.545996}, "location": {"left": 171, "width": 17, "height": 81, "top": 40}}, {"words": "\u6027\u522b\u7537\u6c11\u65cf\u50a3", "probability": {"average": 0.941754, "variance": 0.006905, "min": 0.781344}, "location": {"left": 146, "width": 16, "height": 110, "top": 41}}, {"words": "\u51fa\u751f1979\u5e747\u670826\u65e5", "probability": {"average": 0.998447, "variance": 4e-06, "min": 0.993365}, "location": {"left": 127, "width": 12, "height": 132, "top": 43}}, {"words": "\u4f4f\u5740\u4e91\u5357\u7701\u6012\u6c5f\u5088\u5088\u65cf\u81ea\u6cbb\u5dde", "probability": {"average": 0.923728, "variance": 0.028029, "min": 0.475803}, "location": {"left": 102, "width": 14, "height": 159, "top": 42}}, {"words": "\u6cf8\u6c34\u53bf\u4e0a\u6c5f\u4e61\u871c\u82f1\u6751\u767e\u5bb6", "probability": {"average": 0.985422, "variance": 0.001345, "min": 0.870093}, "location": {"left": 87, "width": 14, "height": 123, "top": 78}}, {"words": "\u8d5b\u7ec434\u53f7", "probability": {"average": 0.929065, "variance": 0.019465, "min": 0.650047}, "location": {"left": 72, "width": 13, "height": 48, "top": 79}}, {"words": "\u516c\u6c11\u8eab\u4efd\u53f7\u7801533321197907260617", "probability": {"average": 0.999775, "variance": 0.0, "min": 0.999241}, "location": {"left": 46, "width": 14, "height": 238, "top": 45}}]}