{"words_result_num": 6, "direction": 0, "log_id": 6012798518064910990, "words_result": [{"location": {"left": 21, "top": 115, "width": 64, "height": 15}, "probability": {"min": 0.993712, "average": 0.998039, "variance": 6e-06}, "words": "\u540d\u8d75\u827e\u793e"}, {"location": {"left": 23, "top": 138, "width": 38, "height": 9}, "probability": {"min": 0.56854, "average": 0.849891, "variance": 0.0396}, "words": "\u6027\u522b\u7537"}, {"location": {"left": 9, "top": 147, "width": 124, "height": 20}, "probability": {"min": 0.875841, "average": 0.959056, "variance": 0.001656}, "words": "\u751f192\u5e746\u670830\u65e5"}, {"location": {"left": 26, "top": 171, "width": 127, "height": 13}, "probability": {"min": 0.510606, "average": 0.905183, "variance": 0.026611}, "words": "\u4f7f\u5740\u4e91\u5357\u7701\u4e34\u6ca7\u5e02\u6ca7\u6e90\u4f0d\u65cf\u81ea"}, {"location": {"left": 56, "top": 183, "width": 96, "height": 13}, "probability": {"min": 0.672627, "average": 0.919567, "variance": 0.011416}, "words": "\u6cbb\u53bf\u52a9\u7701\u9547\u8292\u9633\u6751\u59d4\u4f1a\u4e09"}, {"location": {"left": 30, "top": 214, "width": 189, "height": 17}, "probability": {"min": 0.848595, "average": 0.985764, "variance": 0.00133}, "words": "\u516c\u6c11\u8eab\u4efd\u53f7\u5988533528198206300735"}]}