{"log_id": 2366526123067895373, "direction": 0, "words_result": [{"location": {"left": 198, "height": 39, "width": 259, "top": 416}, "probability": {"min": 0.968277, "variance": 0.000144, "average": 0.990506}, "words": "\u59d3\u540d\u6881\u79cb\u52c7"}, {"location": {"left": 198, "height": 29, "width": 161, "top": 482}, "probability": {"min": 0.944118, "variance": 0.00061, "average": 0.978974}, "words": "\u6027\u522b\u7537"}, {"location": {"left": 425, "height": 29, "width": 138, "top": 482}, "probability": {"min": 0.416285, "variance": 0.065021, "average": 0.773124}, "words": "\u6c11\u65cf\u58ee"}, {"location": {"left": 198, "height": 35, "width": 455, "top": 534}, "probability": {"min": 0.645405, "variance": 0.011623, "average": 0.938299}, "words": "\u51fa\u751f1995\u5e742\u67081\u65e5"}, {"location": {"left": 188, "height": 50, "width": 548, "top": 587}, "probability": {"min": 0.564684, "variance": 0.019164, "average": 0.904185}, "words": "\u67f1\u5740\u5e7f\u897f\u9e7f\u5be8\u53bf\u9e7f\u585e\u9547\u9f99\u576a\u6751"}, {"location": {"left": 315, "height": 34, "width": 274, "top": 636}, "probability": {"min": 0.560829, "variance": 0.019903, "average": 0.921844}, "words": "\u9f99\u53e3\u5c6f23\u53f7\u4e4b\u4e8c"}, {"location": {"left": 185, "height": 47, "width": 884, "top": 740}, "probability": {"min": 0.975522, "variance": 4.9e-05, "average": 0.995648}, "words": "\u516c\u6c11\u8eab\u4efd\u53f7\u7801450223199502012010"}], "words_result_num": 7}