{"log_id": 5748325189543825453, "direction": 0, "words_result": [{"location": {"left": 89, "height": 76, "width": 311, "top": 334}, "probability": {"min": 0.486077, "variance": 0.040055, "average": 0.88344}, "words": "\u59d3\u540d\u8096\u94a7\u8000"}, {"location": {"left": 82, "height": 83, "width": 431, "top": 453}, "probability": {"min": 0.615571, "variance": 0.025968, "average": 0.85382}, "words": "\u6027\u522b\u7537\u6c11\u585e\u6c49"}, {"location": {"left": 85, "height": 82, "width": 529, "top": 572}, "probability": {"min": 0.94742, "variance": 0.000268, "average": 0.982739}, "words": "\u51fa\u751f1995\u5e748\u670827\u65e5"}, {"location": {"left": 83, "height": 75, "width": 864, "top": 704}, "probability": {"min": 0.673432, "variance": 0.016037, "average": 0.916219}, "words": "\u4f4f\u5740\u6e56\u5357\u7701\u54ea\u5dde\u5e02\u82cf\u4ed9\u533a\u56db\u666e"}, {"location": {"left": 221, "height": 66, "width": 276, "top": 789}, "probability": {"min": 0.388257, "variance": 0.045492, "average": 0.91069}, "words": "\u5e84\u7efc\u5408\u697c19\u53f7"}, {"location": {"left": 85, "height": 79, "width": 955, "top": 1013}, "probability": {"min": 0.588783, "variance": 0.007059, "average": 0.974494}, "words": "\u516c\u6c11\u8eab\u4efd\u53f7\u7801431002199508270031"}], "words_result_num": 6}