{"log_id": 2733761041859871021, "direction": 0, "words_result": [{"probability": {"average": 0.95725, "variance": 0.005951, "min": 0.803124}, "location": {"height": 22, "left": 25, "width": 91, "top": 27}, "words": "\u59d3\u540d\u595a\u52a1\u5e05"}, {"probability": {"average": 0.986213, "variance": 0.000193, "min": 0.96473}, "location": {"height": 16, "left": 24, "width": 122, "top": 56}, "words": "\u6027\u522b\u7537\u6c11\u65cf\u6c49"}, {"probability": {"average": 0.91463, "variance": 0.020175, "min": 0.507188}, "location": {"height": 23, "left": 25, "width": 147, "top": 80}, "words": "\u51fa\u751f195\u5e748\u670821\u65e5"}, {"probability": {"average": 0.954751, "variance": 0.014192, "min": 0.543574}, "location": {"height": 18, "left": 25, "width": 242, "top": 105}, "words": "\u4f73\u5740\u957f\u6c99\u5e02\u5f00\u798f\u533a\u8299\u84c9\u5317\u8def74"}, {"probability": {"average": 0.999922, "variance": 0.0, "min": 0.999853}, "location": {"height": 17, "left": 61, "width": 24, "top": 122}, "words": "7\u53f7"}, {"probability": {"average": 0.999134, "variance": 6e-06, "min": 0.987582}, "location": {"height": 19, "left": 24, "width": 266, "top": 171}, "words": "\u516c\u6c11\u8eab\u4efd\u53f7\u7801430105198508218697"}], "words_result_num": 6}